hello/__init__.py
hello/main.py
hello_dummy-0.0.1.dist-info/METADATA
hello_dummy-0.0.1.dist-info/WHEEL
hello_dummy-0.0.1.dist-info/top_level.txt
hello_dummy-0.0.1.dist-info/RECORD
