Metadata-Version: 2.1
Name: hello-dummy
Version: 0.0.1
Summary: JUST A SAMPLE HELLO PACKAGE
Home-page: UNKNOWN
Author: Lokji
Author-email: <temp@gmail.com>
License: UNKNOWN
Keywords: python,numpy
Platform: UNKNOWN
Classifier: Programming Language :: Python :: 3
Classifier: License :: OSI Approved :: MIT License
Classifier: Operating System :: OS Independent
Requires-Dist: numpy
